image_processing/__init__.py
image_processing/processing/__init__.py
image_processing/processing/combination.py
image_processing/processing/transformation.py
image_processing/utils/__init__.py
image_processing/utils/io.py
image_processing/utils/plot.py
py_image_processing/__init__.py
py_image_processing/processing/__init__.py
py_image_processing/processing/combination.py
py_image_processing/processing/transformation.py
py_image_processing/utils/__init__.py
py_image_processing/utils/io.py
py_image_processing/utils/plot.py
py_img_processing/__init__.py
py_img_processing/processing/__init__.py
py_img_processing/processing/combination.py
py_img_processing/processing/transformation.py
py_img_processing/utils/__init__.py
py_img_processing/utils/io.py
py_img_processing/utils/plot.py
py_image_processing-0.0.2.dist-info/METADATA
py_image_processing-0.0.2.dist-info/WHEEL
py_image_processing-0.0.2.dist-info/top_level.txt
py_image_processing-0.0.2.dist-info/RECORD
