Metadata-Version: 2.1
Name: py-image-processing
Version: 0.0.2
Summary: Pacote para processamento de imagens
Home-page: https://github.com/lucasbrowser/pack_processing_image_python
Author: Lucas de Souza Oliveira
Author-email: lucasdicasmt@gmail.com
License: UNKNOWN
Platform: UNKNOWN
Requires-Python: >=3.6
Requires-Dist: matplotlib
Requires-Dist: numpy
Requires-Dist: scikit-image (>=0.16.1)
